lambdex/__init__.py
lambdex/__main__.py
lambdex/version.py
lambdex/bin/__init__.py
lambdex/bin/lambdex.py
lambdex/resources/__init__.py
lambdex/resources/lambdex_handler.py
lambdex-0.2.0.dist-info/entry_points.txt
lambdex-0.2.0.dist-info/LICENSE
lambdex-0.2.0.dist-info/WHEEL
lambdex-0.2.0.dist-info/METADATA
lambdex-0.2.0.dist-info/RECORD
